wagascianpy/__init__.py
wagascianpy/analysis/__init__.py
wagascianpy/analysis/analysis.py
wagascianpy/analysis/analyzer.py
wagascianpy/analysis/apply_detector_flags.py
wagascianpy/analysis/beam_summary_data.py
wagascianpy/analysis/mhistory2sqlite.py
wagascianpy/analysis/sanity_check.py
wagascianpy/analysis/spill.py
wagascianpy/database/__init__.py
wagascianpy/database/bsddb.py
wagascianpy/database/db_record.py
wagascianpy/database/my_tinydb.py
wagascianpy/database/wagascidb.py
wagascianpy/plotting/__init__.py
wagascianpy/plotting/colors.py
wagascianpy/plotting/configuration.py
wagascianpy/plotting/detector.py
wagascianpy/plotting/graph.py
wagascianpy/plotting/harvest.py
wagascianpy/plotting/marker.py
wagascianpy/plotting/parse_args.py
wagascianpy/plotting/plotter.py
wagascianpy/plotting/topology.py
wagascianpy/program/__init__.py
wagascianpy/program/director.py
wagascianpy/program/program.py
wagascianpy/program/program_builder.py
wagascianpy/pyrmod/CCC.py
wagascianpy/pyrmod/__init__.py
wagascianpy/pyrmod/pyrmod.py
wagascianpy/utils/__init__.py
wagascianpy/utils/acq_config_xml.py
wagascianpy/utils/change_bitstream.py
wagascianpy/utils/classproperty.py
wagascianpy/utils/configuration.py
wagascianpy/utils/environment.py
wagascianpy/utils/topology.py
wagascianpy/utils/treenames.py
wagascianpy/utils/utils.py
wagascianpy/viewer/__init__.py
wagascianpy/viewer/configuration.py
wagascianpy/viewer/downloader.py
wagascianpy/viewer/gui.ui
wagascianpy/viewer/import_tkinter.py
wagascianpy/viewer/parse_args.py
wagascianpy/viewer/show_run_info.py
wagascianpy/viewer/topology.py
wagascianpy/viewer/topology_generator.py
wagascianpy/viewer/utils.py
wagascianpy-0.3.10.data/scripts/apply_detector_flags.py
wagascianpy-0.3.10.data/scripts/beam_summary_data.py
wagascianpy-0.3.10.data/scripts/ch_vs_charge.py
wagascianpy-0.3.10.data/scripts/ch_vs_numhit.py
wagascianpy-0.3.10.data/scripts/gain_calibration.py
wagascianpy-0.3.10.data/scripts/gain_check.py
wagascianpy-0.3.10.dist-info/LICENSE.md
wagascianpy-0.3.10.dist-info/METADATA
wagascianpy-0.3.10.dist-info/WHEEL
wagascianpy-0.3.10.dist-info/top_level.txt
wagascianpy-0.3.10.dist-info/zip-safe
wagascianpy-0.3.10.dist-info/RECORD
