Metadata-Version: 2.1
Name: wagascianpy
Version: 0.3.10
Summary: WAGASCI ANPAN for Python
Home-page: https://git.t2k.org/wagasci_babymind/WagasciAnpy
Author: Pintaudi Giorgio
Author-email: giorgio.pimpa@gmail.com
License: GPLv3
Keywords: WAGASCI ANPAN for Python
Classifier: Development Status :: 4 - Beta
Classifier: Environment :: Console
Classifier: Environment :: X11 Applications
Classifier: Intended Audience :: System Administrators
Classifier: Programming Language :: Python :: 2.7
Classifier: Programming Language :: Python :: 3.4
Classifier: Programming Language :: Python :: 3.5
Classifier: Programming Language :: Python :: 3.6
Classifier: Programming Language :: Python :: 3.7
Classifier: Programming Language :: Python :: 3.8
Classifier: Programming Language :: Python :: 3.9
Classifier: Programming Language :: Python :: 3.10
Classifier: Programming Language :: Python :: 3.11
Classifier: Programming Language :: Python :: 3.12
Classifier: License :: OSI Approved :: GNU General Public License v3 (GPLv3)
Classifier: Operating System :: Unix
License-File: LICENSE.md
Requires-Dist: setuptools >=72.1.0
Requires-Dist: bitarray >=0.8.1
Requires-Dist: six >=1.16.0
Requires-Dist: paramiko >=3.3.2
Requires-Dist: scp >=0.7.1
Requires-Dist: pytz >=2024.2
Requires-Dist: tinydb >=3.15.2
Requires-Dist: recordclass >=0.13.2
Requires-Dist: pyfakefs >=3.7.2
Requires-Dist: numpy >=1.26.4
Requires-Dist: undecorated >=0.3.0
Requires-Dist: dependency-injector >=3.15.6
Requires-Dist: inflection >=0.3.1
Requires-Dist: pygubu >=0.35.5
Requires-Dist: mock >=1.0.15.6
Requires-Dist: typing >=3.5.2.2 ; python_version < "3.5"
Provides-Extra: with_borg
Requires-Dist: borgbackup >=1.1.11 ; extra == 'with_borg'
